MANIFEST.in
README.md
setup.cfg
setup.py
flask_sqlite_admin/__init__.py
flask_sqlite_admin/__init__.pyc
flask_sqlite_admin/core.py
flask_sqlite_admin/core.pyc
flask_sqlite_admin/sqliteFunctions.py
flask_sqlite_admin/sqliteFunctions.pyc
flask_sqlite_admin.egg-info/PKG-INFO
flask_sqlite_admin.egg-info/SOURCES.txt
flask_sqlite_admin.egg-info/dependency_links.txt
flask_sqlite_admin.egg-info/requires.txt
flask_sqlite_admin.egg-info/top_level.txt
flask_sqlite_admin/static/css/bootstrap.min.css
flask_sqlite_admin/static/css/sqliteAdmin.css
flask_sqlite_admin/static/fonts/glyphicons-halflings-regular.eot
flask_sqlite_admin/static/fonts/glyphicons-halflings-regular.svg
flask_sqlite_admin/static/fonts/glyphicons-halflings-regular.ttf
flask_sqlite_admin/static/fonts/glyphicons-halflings-regular.woff
flask_sqlite_admin/static/fonts/glyphicons-halflings-regular.woff2
flask_sqlite_admin/static/js/bootstrap.min.js
flask_sqlite_admin/static/js/sqliteAdmin.js
flask_sqlite_admin/templates/base.html
flask_sqlite_admin/templates/sqlite.html
flask_sqlite_admin/templates/sqlite_ajax.html
flask_sqlite_admin/tests/__init__.py
flask_sqlite_admin/tests/core_test.py
flask_sqlite_admin/tests/sqliteFunctions_test.py