Metadata-Version: 1.1
Name: flask-sqlite-admin
Version: 0.3
Summary: SQLite DB Management Blueprint for Flask Applications
Home-page: https://github.com/twaldear/flask-sqlite-admin
Author: Tristan Waldear
Author-email: trwaldear@gmail.com
License: MIT
Download-URL: https://github.com/twaldear/flask-sqlite-admin/tarball/0.1
Keywords: flask,sqlite,database,admin
Platform: UNKNOWN
Classifier: Development Status :: 4 - Beta
Classifier: Framework :: Flask
Classifier: License :: OSI Approved :: MIT License
Classifier: Operating System :: OS Independent
Classifier: Programming Language :: Python
Classifier: Topic :: Software Development :: Libraries :: Python Modules
